mlbapi/__init__.py
mlbapi/endpoint.py
mlbapi/exceptions.py
mlbapi/utils.py
mlbapi/version.py
mlbapi/data/__init__.py
mlbapi/data/conference.py
mlbapi/data/config.py
mlbapi/data/division.py
mlbapi/data/draft.py
mlbapi/data/game.py
mlbapi/data/gameday.py
mlbapi/data/homerunderby.py
mlbapi/data/league.py
mlbapi/data/people.py
mlbapi/data/schedule.py
mlbapi/data/season.py
mlbapi/data/standings.py
mlbapi/data/stats.py
mlbapi/data/team.py
mlbapi/data/venue.py
mlbapi/object/__init__.py
mlbapi/object/game.py
mlbapi/object/gameday.py
mlbapi/object/standings.py
mlbapi/object/team.py
mlbapi-0.1.4.dist-info/LICENSE
mlbapi-0.1.4.dist-info/METADATA
mlbapi-0.1.4.dist-info/WHEEL
mlbapi-0.1.4.dist-info/top_level.txt
mlbapi-0.1.4.dist-info/RECORD
