Metadata-Version: 2.1
Name: mlbapi
Version: 0.1.4
Summary: A python3 API wrapper for the MLB API at statsmlb.mlb.com
Home-page: https://github.com/trevor-viljoen/mlbapi
Author: Trevor Viljoen
Author-email: trevor.viljoen@gmail.com
License: MIT
Keywords: MLB,MLB API,Major League Baseball,baseball,baseball API,baseball data,baseball scores,baseball statistics,baseball stats
Platform: ANY
Classifier: License :: OSI Approved :: MIT License
Classifier: Environment :: Console
Classifier: Operating System :: OS Independent
Classifier: Programming Language :: Python :: 3
Requires-Python: >=3.6
Requires-Dist: requests
Requires-Dist: python-dateutil
Requires-Dist: inflection
Provides-Extra: dev
Requires-Dist: pytest ; extra == 'dev'
Requires-Dist: pytest-cov ; extra == 'dev'
Requires-Dist: coveralls ; extra == 'dev'
